Metadata-Version: 2.1
Name: extract-codon-alignment
Version: 0.0.1
Summary: To extract some codon positions (1st, 2nd, 3rd) from a CDS alignment.
Home-page: https://github.com/linzhi2013/extract_codon_alignment
Author: Guanliang Meng
Author-email: linzhi2012@gmail.com
License: UNKNOWN
Platform: UNKNOWN
Classifier: Development Status :: 3 - Alpha
Classifier: Intended Audience :: Science/Research
Classifier: Topic :: Scientific/Engineering :: Bio-Informatics
Classifier: License :: OSI Approved :: GNU General Public License v3 or later (GPLv3+)
Classifier: Programming Language :: Python :: 3
Classifier: Operating System :: MacOS :: MacOS X
Classifier: Operating System :: Microsoft :: Windows
Classifier: Operating System :: POSIX :: Linux
Requires-Python: >=3
